src/example_package_jtam/__init__.py
src/example_package_jtam/hello.py
poetry_demo_jtam-0.1.1.dist-info/METADATA
poetry_demo_jtam-0.1.1.dist-info/WHEEL
poetry_demo_jtam-0.1.1.dist-info/entry_points.txt
poetry_demo_jtam-0.1.1.dist-info/RECORD
