Metadata-Version: 2.1
Name: poetry-demo-jtam
Version: 0.1.1
Summary: demo project to show how to use poetry to package and then to publish to pypi
Author: Jason Tam
Author-email: jasontamemail@gmail.com
Requires-Python: >=3.12,<4.0
Classifier: Programming Language :: Python :: 3
Classifier: Programming Language :: Python :: 3.12
